{
  "repair_begin": "2020-10-17 10:08:13.225568",
  "repair_end": "2020-10-17 10:18:35.898332",
  "patches": [
    {
      "target_file": "src/operation.i",
      "fix": "480c480\n<   if (0 == (int )tmp) {\n---\n>   if (0 <= (int )tmp) {\n",
      "edits": [
        "480c480\n<   if (0 == (int )tmp) {\n---\n>   if (0 != (int )tmp) {\n",
        "480c480\n<   if (0 == (int )tmp) {\n---\n>   if (0 <= (int )tmp) {\n"
      ]
    }
  ],
  "stats": {
    "compile success rate": 1.0,
    "edits score": 0.9440608762859234,
    "time score": 0.3027652518339453,
    "score": 2.2468261281198685
  }
}